LICENSE
MANIFEST.in
README.rst
setup.cfg
setup.py
pydesktime/__init__.py
pydesktime/desktime.py
pydesktime.egg-info/PKG-INFO
pydesktime.egg-info/SOURCES.txt
pydesktime.egg-info/dependency_links.txt
pydesktime.egg-info/entry_points.txt
pydesktime.egg-info/not-zip-safe
pydesktime.egg-info/requires.txt
pydesktime.egg-info/top_level.txt
pydesktime/scripts/__init__.py