Metadata-Version: 1.1
Name: pydesktime
Version: 0.1.3
Summary: Module to communicate with Desktime API
Home-page: http://github.com/utek/pydesktime
Author: Łukasz Bołdys
Author-email: mail@utek.pl
License: Copyright (C) 2014 Lukasz Boldys
